{"openapi":"3.0.0","info":{"title":"debug_traceTransaction example","version":"1.0.0","description":"This API example demonstrates how to use the debug_traceTransaction method to retrieve a detailed execution  trace of a transaction, identified by the transaction's hash."},"servers":[{"url":"https://base-mainnet.core.chainstack.com/2fc1de7f08c0465f6a28e3c355e0cb14"}],"paths":{"/":{"post":{"tags":["Debug Operations"],"summary":"debug_traceTransaction","operationId":"traceTransaction","requestBody":{"required":true,"content":{"application/json":{"schema":{"type":"object","required":["jsonrpc","method","id","params"],"properties":{"jsonrpc":{"type":"string","default":"2.0"},"method":{"type":"string","default":"debug_traceTransaction"},"id":{"type":"integer","default":1},"params":{"type":"array","items":{"type":"string"},"default":["0x317888c89fe0914c6d11be51acf758742afbe0cf1fdac11f19d35d6ed652ac29"]}}}}}},"responses":{"200":{"description":"Detailed execution trace of the specified transaction","content":{"application/json":{"schema":{"type":"object","properties":{"jsonrpc":{"type":"string"},"id":{"type":"integer"},"result":{"type":"object","properties":{"structLogs":{"type":"array","items":{"type":"object"},"description":"An array of execution steps (opcodes) taken by the transaction."},"gas":{"type":"integer","description":"The gas provided by the transaction."},"returnValue":{"type":"string","description":"The return value of the transaction, if any."},"gasUsed":{"type":"integer","description":"The total gas used by the transaction."},"failed":{"type":"boolean","description":"Indicates whether the transaction failed."}},"description":"The detailed execution trace of the transaction."}}}}}}}}}},"x-readme":{"explorer-enabled":true,"proxy-enabled":true}}